earendil/__init__.py
earendil/base_email.py
earendil/mailer.py
earendil/markdown_email.py
earendil/plaintext_renderer.py
earendil_mail-0.2.0.dist-info/METADATA
earendil_mail-0.2.0.dist-info/WHEEL
earendil_mail-0.2.0.dist-info/RECORD
