Metadata-Version: 2.1
Name: earendil_mail
Version: 0.2.0
Summary: A Markdown-based HTML email API.
Home-page: https://github.com/ADSteele916/earendil
Author: Alex Steele
Author-email: 45648397+ADSteele916@users.noreply.github.com
Requires-Python: >=3.10,<4.0
Classifier: Development Status :: 3 - Alpha
Classifier: Operating System :: OS Independent
Classifier: Programming Language :: Python :: 3
Classifier: Programming Language :: Python :: 3.10
Classifier: Programming Language :: Python :: 3.11
Classifier: Programming Language :: Python :: 3.12
Requires-Dist: Markdown (>=3.6,<4.0)
Project-URL: Issue Tracker, https://github.com/ADSteele916/earendil/issues
Project-URL: Repository, https://github.com/ADSteele916/earendil
